[
  { "id":"1",
    "zen_id": "Guvi-stu_1",
    "profile_pic": "https://avatars.githubusercontent.com/u/89139024?v=4",
    "name": "GowthamKumar V",
    "email": "vgowtham.kumar8@gmail.com"
  },
  {  "id":"2",
    "zen_id": "Guvi-stu_2",
    "profile_pic": "https://images.unsplash.com/photo-1508835277982-1c1b0e205603?ixlib=rb-1.2.1&raw_url=true&q=80&fm=jpg&crop=entropy&cs=tinysrgb&ixzen_id=MnwxMjA3fDB8MHxwaG90by1wYWdlfHx8fGVufDB8fHx8&auto=format&fit=crop&w=687",
    "name": "rajkumar K",
    "email": "Raj.kumar007@gmail.com"
  },
  { "id":"3",
    "zen_id": "Guvi-stu_3",
    "profile_pic": "https://images.unsplash.com/photo-1494708001911-679f5d15a946?ixlib=rb-1.2.1&raw_url=true&q=80&fm=jpg&crop=entropy&cs=tinysrgb&ixzen_id=MnwxMjA3fDB8MHxwaG90by1wYWdlfHx8fGVufDB8fHx8&auto=format&fit=crop&w=1170",
    "name": "shiva kumar K",
    "email": "shiv8072@gmail.com"
  },
  { "id":"4",
    "zen_id": "Guvi-stu_4",
    "profile_pic": "https://images.unsplash.com/photo-1503443207922-dff7d543fd0e?ixlib=rb-1.2.1&raw_url=true&q=80&fm=jpg&crop=entropy&cs=tinysrgb&ixzen_id=MnwxMjA3fDB8MHxwaG90by1wYWdlfHx8fGVufDB8fHx8&auto=format&fit=crop&w=627",
    "name": "deva raj K",
    "email": "deva89@gmail.com"
  },
  { "id":"5",
    "zen_id": "Guvi-stu_5",
    "profile_pic": "https://images.unsplash.com/photo-1503443207922-dff7d543fd0e?ixlib=rb-1.2.1&raw_url=true&q=80&fm=jpg&crop=entropy&cs=tinysrgb&ixzen_id=MnwxMjA3fDB8MHxwaG90by1wYWdlfHx8fGVufDB8fHx8&auto=format&fit=crop&w=627",
    "name": "karthik P",
    "email": "karthi23@gmail.com"
  },
  { "id":"6",
    "zen_id": "Guvi-stu_6",
    "profile_pic": "https://images.unsplash.com/photo-1519764622345-23439dd774f7?ixlib=rb-1.2.1&raw_url=true&q=80&fm=jpg&crop=entropy&cs=tinysrgb&ixzen_id=MnwxMjA3fDB8MHxwaG90by1wYWdlfHx8fGVufDB8fHx8&auto=format&fit=crop&w=687",
    "name": "ragavendra N",
    "email": "karthi23@gmail.com"
  },
  { "id":"7",
    "zen_id": "Guvi-stu_7",
    "profile_pic": "https://images.unsplash.com/photo-1517530094915-500495b15ade?ixlib=rb-1.2.1&raw_url=true&q=80&fm=jpg&crop=entropy&cs=tinysrgb&ixzen_id=MnwxMjA3fDB8MHxwaG90by1wYWdlfHx8fGVufDB8fHx8&auto=format&fit=crop&w=687",
    "name": "Jeffery B",
    "email": "jeffb86@gmail.com"
  },
  { "id":"8",
    "zen_id": "Guvi-stu_8",
    "profile_pic": "https://images.unsplash.com/photo-1519058082700-08a0b56da9b4?ixlib=rb-1.2.1&raw_url=true&q=80&fm=jpg&crop=entropy&cs=tinysrgb&ixzen_id=MnwxMjA3fDB8MHxwaG90by1wYWdlfHx8fGVufDB8fHx8&auto=format&fit=crop&w=687",
    "name": "john H",
    "email": "john001@gmail.com"
  }, 
  { "id":"9",
    "zen_id": "Guvi-stu_9",
    "profile_pic": "https://images.unsplash.com/photo-1495366691023-cc4eadcc2d7e?ixlib=rb-1.2.1&raw_url=true&q=80&fm=jpg&crop=entropy&cs=tinysrgb&ixzen_id=MnwxMjA3fDB8MHxwaG90by1wYWdlfHx8fGVufDB8fHx8&auto=format&fit=crop&w=687",
    "name": "Dani B",
    "email": "dan88@gmail.com"
  },
  {  "id":"10",
    "zen_id": "Guvi-stu_10",
    "profile_pic": "https://images.unsplash.com/photo-1514626585111-9aa86183ac98?ixlib=rb-1.2.1&raw_url=true&q=80&fm=jpg&crop=entropy&cs=tinysrgb&ixzen_id=MnwxMjA3fDB8MHxwaG90by1wYWdlfHx8fGVufDB8fHx8&auto=format&fit=crop&w=687",
    "name": "Lara B",
    "email": "lara54@gmail.com"
  },
  { "id":"11",
    "zen_id": "Guvi-stu_11",
    "profile_pic": "https://images.unsplash.com/photo-1503185912284-5271ff81b9a8?ixlib=rb-1.2.1&raw_url=true&q=80&fm=jpg&crop=entropy&cs=tinysrgb&ixzen_id=MnwxMjA3fDB8MHxwaG90by1wYWdlfHx8fGVufDB8fHx8&auto=format&fit=crop&w=687",
    "name": "Christy D",
    "email": "Chrish77@gmail.com"
  },
  { "id":"12",
    "zen_id": "Guvi-stu_12",
    "profile_pic": "https://images.unsplash.com/photo-1491349174775-aaafddd81942?ixlib=rb-1.2.1&raw_url=true&q=80&fm=jpg&crop=entropy&cs=tinysrgb&ixzen_id=MnwxMjA3fDB8MHxwaG90by1wYWdlfHx8fGVufDB8fHx8&auto=format&fit=crop&w=687",
    "name": "Jenny H",
    "email": "jen85@gmail.com"
  },
  { "id":"13",
    "zen_id": "Guvi-stu_13",
    "profile_pic": "https://images.unsplash.com/photo-1536766768598-e09213fdcf22?ixlib=rb-1.2.1&raw_url=true&q=80&fm=jpg&crop=entropy&cs=tinysrgb&ixzen_id=MnwxMjA3fDB8MHxwaG90by1wYWdlfHx8fGVufDB8fHx8&auto=format&fit=crop&w=688",
    "name": "Jasmine J",
    "email": "jasmine92@gmail.com"
  },
  {"id":"14",
    "zen_id": "Guvi-stu_14",
    "profile_pic": "https://images.unsplash.com/photo-1509783236416-c9ad59bae472?ixlib=rb-1.2.1&raw_url=true&q=80&fm=jpg&crop=entropy&cs=tinysrgb&ixzen_id=MnwxMjA3fDB8MHxwaG90by1wYWdlfHx8fGVufDB8fHx8&auto=format&fit=crop&w=687",
    "name": "Shofia L",
    "email": "sofi72@gmail.com"
  },
  {"id":"15",
    "zen_id": "Guvi-stu_15",
    "profile_pic": "https://images.unsplash.com/photo-1542027959157-98e6745f4ba7?crop=entropy&cs=tinysrgb&fm=jpg&ixlib=rb-1.2.1&q=80&raw_url=true&ixzen_id=MnwxMjA3fDB8MHxwaG90by1wYWdlfHx8fGVufDB8fHx8&auto=format&fit=crop&w=687",
    "name": "Neha M",
    "email": "lilly57@gmail.com"
  },
  { "id":"16",
    "zen_id": "Guvi-stu_16",
    "profile_pic": "https://images.unsplash.com/photo-1510696089168-f1d31149bdde?crop=entropy&cs=tinysrgb&fm=jpg&ixlib=rb-1.2.1&q=80&raw_url=true&ixzen_id=MnwxMjA3fDB8MHxwaG90by1wYWdlfHx8fGVufDB8fHx8&auto=format&fit=crop&w=1170",
    "name": "Annu C",
    "email": "lilly57@gmail.com"
  },
  {"id":"17",
    "zen_id": "Guvi-stu_17",
    "profile_pic": "https://images.unsplash.com/photo-1524701208119-e91fc2e4c8e5?ixlib=rb-1.2.1&raw_url=true&q=80&fm=jpg&crop=entropy&cs=tinysrgb&ixzen_id=MnwxMjA3fDB8MHxwaG90by1wYWdlfHx8fGVufDB8fHx8&auto=format&fit=crop&w=687",
    "name": "Jenisha O",
    "email": "lilly57@gmail.com"
  },
  {"id":"18",
    "zen_id": "Guvi-stu_18",
    "profile_pic": "https://images.unsplash.com/photo-1613365765813-e29fea16ecaa?crop=entropy&cs=tinysrgb&fm=jpg&ixlib=rb-1.2.1&q=80&raw_url=true&ixzen_id=MnwxMjA3fDB8MHxwaG90by1wYWdlfHx8fGVufDB8fHx8&auto=format&fit=crop&w=765",
    "name": "Sonia H",
    "email": "lilly57@gmail.com"
  },
  { "id":"19",
    "zen_id": "Guvi-stu_19",
    "profile_pic": "https://images.unsplash.com/photo-1601832823286-f4dff34eebc7?crop=entropy&cs=tinysrgb&fm=jpg&ixlib=rb-1.2.1&q=80&raw_url=true&ixzen_id=MnwxMjA3fDB8MHxwaG90by1wYWdlfHx8fGVufDB8fHx8&auto=format&fit=crop&w=626",
    "name": "Reshma B",
    "email": "lilly57@gmail.com"
  },
  { "id":"20",
    "zen_id": "Guvi-stu_20",
    "profile_pic": "https://images.unsplash.com/photo-1647960316872-3efbc08086f1?crop=entropy&cs=tinysrgb&fm=jpg&ixlib=rb-1.2.1&q=80&raw_url=true&ixzen_id=MnwxMjA3fDB8MHxwaG90by1wYWdlfHx8fGVufDB8fHx8&auto=format&fit=crop&w=764",
    "name": "Dhivya M",
    "email": "lilly57@gmail.com"
  }
]
